uripecker/__init__.py
uripecker/__main__.py
uripecker/_meta.py
uripecker/peck.py
uripecker/py.typed
uripecker-0.0.16.dist-info/LICENSE.md
uripecker-0.0.16.dist-info/METADATA
uripecker-0.0.16.dist-info/WHEEL
uripecker-0.0.16.dist-info/top_level.txt
uripecker-0.0.16.dist-info/RECORD
